voxbridge/__init__.py
voxbridge/benchmark.py
voxbridge/blender_cleanup.py
voxbridge/cli.py
voxbridge/converter.py
voxbridge/converter_backup.py
voxbridge/converter_broken.py
voxbridge/converter_old.py
voxbridge/platform_profiles.py
voxbridge/texture_optimizer.py
voxbridge/gui/__init__.py
voxbridge/gui/app.py
voxbridge-1.0.7.dist-info/licenses/LICENSE
voxbridge-1.0.7.dist-info/METADATA
voxbridge-1.0.7.dist-info/WHEEL
voxbridge-1.0.7.dist-info/entry_points.txt
voxbridge-1.0.7.dist-info/top_level.txt
voxbridge-1.0.7.dist-info/RECORD
