Metadata-Version: 2.4
Name: voxbridge
Version: 1.0.7
Summary: VoxBridge: convert VoxEdit glTF/GLB assets to engine-ready files for Unity and Roblox
Author-email: "Abdulkareem Oyeneye/Dapps over Apps." <team@dappsoverapps.com>
License: MIT
Project-URL: Homepage, https://github.com/Supercoolkayy/voxbridge
Project-URL: Documentation, https://supercoolkayy.github.io/voxbridge/
Project-URL: Issues, https://github.com/Supercoolkayy/voxbridge/issues
Project-URL: Source, https://github.com/Supercoolkayy/voxbridge
Project-URL: Repository, https://github.com/Supercoolkayy/voxbridge
Keywords: gltf,glb,voxedit,unity,roblox,3d,converter,assets
Classifier: Programming Language :: Python :: 3
Classifier: Programming Language :: Python :: 3.9
Classifier: Programming Language :: Python :: 3.10
Classifier: Programming Language :: Python :: 3.11
Classifier: Programming Language :: Python :: 3.12
Classifier: Programming Language :: Python :: 3.13
Classifier: License :: OSI Approved :: MIT License
Classifier: Operating System :: OS Independent
Classifier: Topic :: Multimedia :: Graphics :: 3D Modeling
Classifier: Topic :: Software Development :: Libraries :: Python Modules
Classifier: Intended Audience :: Developers
Classifier: Intended Audience :: End Users/Desktop
Requires-Python: >=3.9
License-File: LICENSE
Requires-Dist: rich<14.0.0,>=13.0.0
Requires-Dist: typer<1.0.0,>=0.12.0
Requires-Dist: pygltflib>=1.16.0
Requires-Dist: Pillow>=10.0.0
Requires-Dist: numpy>=1.24.0
Requires-Dist: scipy>=1.10.0
Requires-Dist: jsonschema>=4.21.0
Dynamic: license-file
